README.rst
setup.py
example_cli_python.egg-info/PKG-INFO
example_cli_python.egg-info/SOURCES.txt
example_cli_python.egg-info/dependency_links.txt
example_cli_python.egg-info/entry_points.txt
example_cli_python.egg-info/top_level.txt
hello/__init__.py
hello/__main__.py
hello/hello.py