Metadata-Version: 1.0
Name: example-cli-python
Version: 1.0.1
Summary: Python command line example package
Home-page: https://github.com/ojixzzz/example-cli-python
Author: Oji Setyawan
Author-email: ojixzzz@gmail.com
License: UNKNOWN
Platform: UNKNOWN
